requests_guard/__init__.py
requests_guard/requests_guard.py
requests_guard-0.1.0.dist-info/DESCRIPTION.rst
requests_guard-0.1.0.dist-info/top_level.txt
requests_guard-0.1.0.dist-info/WHEEL
requests_guard-0.1.0.dist-info/METADATA
requests_guard-0.1.0.dist-info/RECORD
requests_guard-0.1.0.dist-info/metadata.json
