Metadata-Version: 2.0
Name: requests-guard
Version: 0.1.0
Summary: requests-guard is a small library that allows you to impose size and time limits on your HTTP requests.
Home-page: https://github.com/skorokithakis/requests-guard
Author: Stavros Korokithakis
Author-email: hi@stavros.io
License: BSD
Keywords: requests-guard
Platform: UNKNOWN
Classifier: Development Status :: 2 - Pre-Alpha
Classifier: Intended Audience :: Developers
Classifier: License :: OSI Approved :: BSD License
Classifier: Natural Language :: English
Classifier: Programming Language :: Python :: 2
Classifier: Programming Language :: Python :: 2.6
Classifier: Programming Language :: Python :: 2.7
Classifier: Programming Language :: Python :: 3
Classifier: Programming Language :: Python :: 3.3
Classifier: Programming Language :: Python :: 3.4
Requires-Dist: requests
